memorable/__init__.py
memorable/_poet.py
memorable/_resources/adjectives.txt
memorable/_resources/adverbs.txt
memorable/_resources/names.txt
memorable/_resources/nouns/alcohols.txt
memorable/_resources/nouns/animals.txt
memorable/_resources/nouns/celestials.txt
memorable/_resources/nouns/dinosaurs.txt
memorable/_resources/nouns/elements.txt
memorable/_resources/nouns/fish.txt
memorable/_resources/nouns/foods.txt
memorable/_resources/nouns/fruits.txt
memorable/_resources/nouns/geographies.txt
memorable/_resources/nouns/households.txt
memorable/_resources/nouns/investments.txt
memorable/_resources/nouns/literature.txt
memorable/_resources/nouns/mythical.txt
memorable/_resources/nouns/occupations.txt
memorable/_resources/nouns/organs.txt
memorable/_resources/nouns/places.txt
memorable/_resources/nouns/relations.txt
memorable/_resources/nouns/rocks.txt
memorable/_resources/nouns/royalty.txt
memorable/_resources/nouns/tools.txt
memorable/_resources/nouns/transports.txt
memorable/_resources/nouns/trees.txt
memorable/_resources/nouns/vegtables.txt
memorable/_resources/nouns/water_bodies.txt
memorable/_resources/verbs.txt
memorable/_word_bank.py
memorable-1.0.3.dist-info/WHEEL
memorable-1.0.3.dist-info/METADATA
memorable-1.0.3.dist-info/RECORD
