Metadata-Version: 2.1
Name: memorable
Version: 1.0.3
Summary: A library for creating memorable strings.
Home-page: https://gitlab.com/kjschiroo/memorable
License: MIT
Author: Kevin Schiroo
Author-email: kjschiroo@gmail.com
Requires-Python: >=3.8,<4.0
Classifier: License :: OSI Approved :: MIT License
Classifier: Programming Language :: Python :: 3
Classifier: Programming Language :: Python :: 3.8
Project-URL: Repository, https://gitlab.com/kjschiroo/memorable
